[  {
    "name": "Thermalright Peerless Assassin 120 SE",
    "price": 34.9,
    "rpm": 1550,
    "noise_level": 25.6,
    "color": "Black / Silver",
    "size": null,
    "stock": 15
  },
  {
    "name": "ARCTIC Liquid Freezer III Pro 360",
    "price": 84.99,
    "rpm": [
      600,
      3000
    ],
    "noise_level": null,
    "color": "Black",
    "size": 360,
    "stock": 73
  },
  {
    "name": "Cooler Master Hyper 212 Black Edition",
    "price": 25.99,
    "rpm": [
      650,
      2000
    ],
    "noise_level": [
      6.5,
      26
    ],
    "color": "Black",
    "size": null,
    "stock": 70
  },
  {
    "name": "Thermalright Phantom Spirit 120 SE ARGB",
    "price": 37.9,
    "rpm": 1500,
    "noise_level": 25.6,
    "color": "Black / Silver",
    "size": null,
    "stock": 12
  },
  {
    "name": "Thermalright Aqua Elite V3",
    "price": 54.9,
    "rpm": 1500,
    "noise_level": 25.6,
    "color": "Black",
    "size": 360,
    "stock": 85
  },
  {
    "name": "Noctua NH-D15 chromax.black",
    "price": 139.94,
    "rpm": [
      300,
      1500
    ],
    "noise_level": [
      19.2,
      24.6
    ],
    "color": "Black",
    "size": null,
    "stock": 40
  },
  {
    "name": "NZXT Kraken 360",
    "price": 179.99,
    "rpm": [
      500,
      1800
    ],
    "noise_level": [
      17.9,
      30.6
    ],
    "color": "Black",
    "size": 360,
    "stock": 14
  },
  {
    "name": "Corsair NAUTILUS 360 RS ARGB",
    "price": 129.99,
    "rpm": 2100,
    "noise_level": 34,
    "color": "Black",
    "size": 360,
    "stock": 8
  },
  {
    "name": "ARCTIC Liquid Freezer III 360 A-RGB",
    "price": 159.99,
    "rpm": [
      200,
      2000
    ],
    "noise_level": null,
    "color": "Black",
    "size": 360,
    "stock": 20
  }]